aboutcode/hashid/CHANGELOG.rst
aboutcode/hashid/README.rst
aboutcode/hashid/__init__.py
aboutcode/hashid/__init__.py.ABOUT
aboutcode_hashid-0.2.0.dist-info/WHEEL
aboutcode_hashid-0.2.0.dist-info/METADATA
aboutcode_hashid-0.2.0.dist-info/NOTICE
aboutcode_hashid-0.2.0.dist-info/python.LICENSE
aboutcode_hashid-0.2.0.dist-info/apache-2.0.LICENSE
aboutcode_hashid-0.2.0.dist-info/RECORD
