Metadata-Version: 2.1
Name: aboutcode.hashid
Version: 0.2.0
Summary: A library for aboutcode hash-based identifiers for VCID, and PURLs
Keywords: purl,Package-URL,open source,package,sca,scan,VCID,hash
Author-email: "AboutCode, nexB Inc. and others" <info@aboutcode.org>
Requires-Python: >=3.8
Classifier: Development Status :: 5 - Production/Stable
Classifier: Intended Audience :: Developers
Classifier: Programming Language :: Python :: 3
Classifier: Programming Language :: Python :: 3 :: Only
Classifier: Topic :: Software Development
Classifier: Topic :: Utilities
Requires-Dist: packageurl_python >= 0.15.6
Project-URL: Homepage, https://github.com/aboutcode-org/vulnerablecode
